statistix/__init__.py
statistix-0.0.0.dist-info/METADATA
statistix-0.0.0.dist-info/WHEEL
statistix-0.0.0.dist-info/top_level.txt
statistix-0.0.0.dist-info/RECORD
